{
  "transcript": "YES MY BOY GET MY THINGS READY GET YOURS READY WE'RE DEPARTING IN TWO HOURS AS MASTER WISHES CONSEIL REPLIED SERENELY WE HAVEN'T A MOMENT TO LOSE PACK AS MUCH INTO MY TRUNK AS YOU CAN MY TRAVELING KIT MY SUITS SHIRTS AND SOCKS",
  "words": [
    {
      "alignedWord": "yes",
      "case": "success",
      "end": 0.6799999999999999,
      "endOffset": 3,
      "phones": [
        {
          "duration": 0.11,
          "phone": "y_B"
        },
        {
          "duration": 0.1,
          "phone": "eh_I"
        },
        {
          "duration": 0.1,
          "phone": "s_E"
        }
      ],
      "start": 0.37,
      "startOffset": 0,
      "word": "YES"
    },
    {
      "alignedWord": "my",
      "case": "success",
      "end": 0.8600000000000001,
      "endOffset": 6,
      "phones": [
        {
          "duration": 0.07,
          "phone": "m_B"
        },
        {
          "duration": 0.11,
          "phone": "ay_E"
        }
      ],
      "start": 0.68,
      "startOffset": 4,
      "word": "MY"
    },
    {
      "alignedWord": "boy",
      "case": "success",
      "end": 1.24,
      "endOffset": 10,
      "phones": [
        {
          "duration": 0.08,
          "phone": "b_B"
        },
        {
          "duration": 0.3,
          "phone": "oy_E"
        }
      ],
      "start": 0.86,
      "startOffset": 7,
      "word": "BOY"
    },
    {
      "alignedWord": "get",
      "case": "success",
      "end": 1.44,
      "endOffset": 14,
      "phones": [
        {
          "duration": 0.08,
          "phone": "g_B"
        },
        {
          "duration": 0.04,
          "phone": "ih_I"
        },
        {
          "duration": 0.05,
          "phone": "t_E"
        }
      ],
      "start": 1.27,
      "startOffset": 11,
      "word": "GET"
    },
    {
      "alignedWord": "my",
      "case": "success",
      "end": 1.58,
      "endOffset": 17,
      "phones": [
        {
          "duration": 0.03,
          "phone": "m_B"
        },
        {
          "duration": 0.11,
          "phone": "ay_E"
        }
      ],
      "start": 1.44,
      "startOffset": 15,
      "word": "MY"
    },
    {
      "alignedWord": "things",
      "case": "success",
      "end": 1.9100000000000001,
      "endOffset": 24,
      "phones": [
        {
          "duration": 0.07,
          "phone": "th_B"
        },
        {
          "duration": 0.05,
          "phone": "ih_I"
        },
        {
          "duration": 0.1,
          "phone": "ng_I"
        },
        {
          "duration": 0.1,
          "phone": "z_E"
        }
      ],
      "start": 1.59,
      "startOffset": 18,
      "word": "THINGS"
    },
    {
      "alignedWord": "ready",
      "case": "success",
      "end": 2.26,
      "endOffset": 30,
      "phones": [
        {
          "duration": 0.05,
          "phone": "r_B"
        },
        {
          "duration": 0.08,
          "phone": "eh_I"
        },
        {
          "duration": 0.05,
          "phone": "d_I"
        },
        {
          "duration": 0.17,
          "phone": "iy_E"
        }
      ],
      "start": 1.91,
      "startOffset": 25,
      "word": "READY"
    },
    {
      "alignedWord": "get",
      "case": "success",
      "end": 2.49,
      "endOffset": 34,
      "phones": [
        {
          "duration": 0.07,
          "phone": "g_B"
        },
        {
          "duration": 0.06,
          "phone": "ih_I"
        },
        {
          "duration": 0.07,
          "phone": "t_E"
        }
      ],
      "start": 2.29,
      "startOffset": 31,
      "word": "GET"
    },
    {
      "alignedWord": "yours",
      "case": "success",
      "end": 2.7800000000000002,
      "endOffset": 40,
      "phones": [
        {
          "duration": 0.01,
          "phone": "y_B"
        },
        {
          "duration": 0.07,
          "phone": "uh_I"
        },
        {
          "duration": 0.11,
          "phone": "r_I"
        },
        {
          "duration": 0.1,
          "phone": "z_E"
        }
      ],
      "start": 2.49,
      "startOffset": 35,
      "word": "YOURS"
    },
    {
      "alignedWord": "ready",
      "case": "success",
      "end": 3.17,
      "endOffset": 46,
      "phones": [
        {
          "duration": 0.04,
          "phone": "r_B"
        },
        {
          "duration": 0.08,
          "phone": "eh_I"
        },
        {
          "duration": 0.03,
          "phone": "d_I"
        },
        {
          "duration": 0.24,
          "phone": "iy_E"
        }
      ],
      "start": 2.78,
      "startOffset": 41,
      "word": "READY"
    },
    {
      "alignedWord": "we're",
      "case": "success",
      "end": 3.37,
      "endOffset": 52,
      "phones": [
        {
          "duration": 0.07,
          "phone": "w_B"
        },
        {
          "duration": 0.05,
          "phone": "er_E"
        }
      ],
      "start": 3.25,
      "startOffset": 47,
      "word": "WE'RE"
    },
    {
      "alignedWord": "departing",
      "case": "success",
      "end": 3.9000000000000004,
      "endOffset": 62,
      "phones": [
        {
          "duration": 0.06,
          "phone": "d_B"
        },
        {
          "duration": 0.04,
          "phone": "ih_I"
        },
        {
          "duration": 0.08,
          "phone": "p_I"
        },
        {
          "duration": 0.07,
          "phone": "aa_I"
        },
        {
          "duration": 0.06,
          "phone": "r_I"
        },
        {
          "duration": 0.05,
          "phone": "t_I"
        },
        {
          "duration": 0.08,
          "phone": "ih_I"
        },
        {
          "duration": 0.09,
          "phone": "ng_E"
        }
      ],
      "start": 3.37,
      "startOffset": 53,
      "word": "DEPARTING"
    },
    {
      "alignedWord": "in",
      "case": "success",
      "end": 4.0,
      "endOffset": 65,
      "phones": [
        {
          "duration": 0.05,
          "phone": "ih_B"
        },
        {
          "duration": 0.04,
          "phone": "n_E"
        }
      ],
      "start": 3.91,
      "startOffset": 63,
      "word": "IN"
    },
    {
      "alignedWord": "two",
      "case": "success",
      "end": 4.25,
      "endOffset": 69,
      "phones": [
        {
          "duration": 0.11,
          "phone": "t_B"
        },
        {
          "duration": 0.14,
          "phone": "uw_E"
        }
      ],
      "start": 4.0,
      "startOffset": 66,
      "word": "TWO"
    },
    {
      "alignedWord": "hours",
      "case": "success",
      "end": 4.76,
      "endOffset": 75,
      "phones": [
        {
          "duration": 0.19,
          "phone": "aw_B"
        },
        {
          "duration": 0.14,
          "phone": "er_I"
        },
        {
          "duration": 0.18,
          "phone": "z_E"
        }
      ],
      "start": 4.25,
      "startOffset": 70,
      "word": "HOURS"
    },
    {
      "alignedWord": "as",
      "case": "success",
      "end": 5.7299999999999995,
      "endOffset": 78,
      "phones": [
        {
          "duration": 0.14,
          "phone": "ae_B"
        },
        {
          "duration": 0.08,
          "phone": "z_E"
        }
      ],
      "start": 5.51,
      "startOffset": 76,
      "word": "AS"
    },
    {
      "alignedWord": "master",
      "case": "success",
      "end": 6.090000000000001,
      "endOffset": 85,
      "phones": [
        {
          "duration": 0.06,
          "phone": "m_B"
        },
        {
          "duration": 0.08,
          "phone": "ae_I"
        },
        {
          "duration": 0.07,
          "phone": "s_I"
        },
        {
          "duration": 0.07,
          "phone": "t_I"
        },
        {
          "duration": 0.08,
          "phone": "er_E"
        }
      ],
      "start": 5.73,
      "startOffset": 79,
      "word": "MASTER"
    },
    {
      "alignedWord": "wishes",
      "case": "success",
      "end": 6.66,
      "endOffset": 92,
      "phones": [
        {
          "duration": 0.08,
          "phone": "w_B"
        },
        {
          "duration": 0.09,
          "phone": "ih_I"
        },
        {
          "duration": 0.1,
          "phone": "sh_I"
        },
        {
          "duration": 0.1,
          "phone": "ih_I"
        },
        {
          "duration": 0.2,
          "phone": "z_E"
        }
      ],
      "start": 6.09,
      "startOffset": 86,
      "word": "WISHES"
    },
    {
      "alignedWord": "<unk>",
      "case": "success",
      "end": 7.210000000000001,
      "endOffset": 100,
      "phones": [
        {
          "duration": 0.48,
          "phone": "oov_S"
        }
      ],
      "start": 6.73,
      "startOffset": 93,
      "word": "CONSEIL"
    },
    {
      "alignedWord": "replied",
      "case": "success",
      "end": 7.54,
      "endOffset": 108,
      "phones": [
        {
          "duration": 0.04,
          "phone": "r_B"
        },
        {
          "duration": 0.07,
          "phone": "iy_I"
        },
        {
          "duration": 0.06,
          "phone": "p_I"
        },
        {
          "duration": 0.06,
          "phone": "l_I"
        },
        {
          "duration": 0.09,
          "phone": "ay_I"
        },
        {
          "duration": 0.01,
          "phone": "d_E"
        }
      ],
      "start": 7.21,
      "startOffset": 101,
      "word": "REPLIED"
    },
    {
      "alignedWord": "<unk>",
      "case": "success",
      "end": 8.19,
      "endOffset": 117,
      "phones": [
        {
          "duration": 0.65,
          "phone": "oov_S"
        }
      ],
      "start": 7.54,
      "startOffset": 109,
      "word": "SERENELY"
    },
    {
      "alignedWord": "we",
      "case": "success",
      "end": 9.43,
      "endOffset": 120,
      "phones": [
        {
          "duration": 0.12,
          "phone": "w_B"
        },
        {
          "duration": 0.08,
          "phone": "iy_E"
        }
      ],
      "start": 9.23,
      "startOffset": 118,
      "word": "WE"
    },
    {
      "alignedWord": "haven't",
      "case": "success",
      "end": 9.749999,
      "endOffset": 128,
      "phones": [
        {
          "duration": 0.04,
          "phone": "hh_B"
        },
        {
          "duration": 0.09,
          "phone": "ae_I"
        },
        {
          "duration": 0.04,
          "phone": "v_I"
        },
        {
          "duration": 0.02,
          "phone": "ah_I"
        },
        {
          "duration": 0.06,
          "phone": "n_I"
        },
        {
          "duration": 0.07,
          "phone": "t_E"
        }
      ],
      "start": 9.429999,
      "startOffset": 121,
      "word": "HAVEN'T"
    },
    {
      "alignedWord": "a",
      "case": "success",
      "end": 9.81,
      "endOffset": 130,
      "phones": [
        {
          "duration": 0.06,
          "phone": "ah_S"
        }
      ],
      "start": 9.75,
      "startOffset": 129,
      "word": "A"
    },
    {
      "alignedWord": "moment",
      "case": "success",
      "end": 10.059999,
      "endOffset": 137,
      "phones": [
        {
          "duration": 0.07,
          "phone": "m_B"
        },
        {
          "duration": 0.07,
          "phone": "ow_I"
        },
        {
          "duration": 0.04,
          "phone": "m_I"
        },
        {
          "duration": 0.04,
          "phone": "ah_I"
        },
        {
          "duration": 0.02,
          "phone": "n_I"
        },
        {
          "duration": 0.01,
          "phone": "t_E"
        }
      ],
      "start": 9.809999,
      "startOffset": 131,
      "word": "MOMENT"
    },
    {
      "alignedWord": "to",
      "case": "success",
      "end": 10.19,
      "endOffset": 140,
      "phones": [
        {
          "duration": 0.07,
          "phone": "t_B"
        },
        {
          "duration": 0.04,
          "phone": "ah_E"
        }
      ],
      "start": 10.08,
      "startOffset": 138,
      "word": "TO"
    },
    {
      "alignedWord": "lose",
      "case": "success",
      "end": 10.67,
      "endOffset": 145,
      "phones": [
        {
          "duration": 0.11,
          "phone": "l_B"
        },
        {
          "duration": 0.15,
          "phone": "uw_I"
        },
        {
          "duration": 0.22,
          "phone": "z_E"
        }
      ],
      "start": 10.19,
      "startOffset": 141,
      "word": "LOSE"
    },
    {
      "alignedWord": "pack",
      "case": "success",
      "end": 11.43,
      "endOffset": 150,
      "phones": [
        {
          "duration": 0.1,
          "phone": "p_B"
        },
        {
          "duration": 0.13,
          "phone": "ae_I"
        },
        {
          "duration": 0.09,
          "phone": "k_E"
        }
      ],
      "start": 11.11,
      "startOffset": 146,
      "word": "PACK"
    },
    {
      "alignedWord": "as",
      "case": "success",
      "end": 11.63,
      "endOffset": 153,
      "phones": [
        {
          "duration": 0.1,
          "phone": "eh_B"
        },
        {
          "duration": 0.07,
          "phone": "z_E"
        }
      ],
      "start": 11.46,
      "startOffset": 151,
      "word": "AS"
    },
    {
      "alignedWord": "much",
      "case": "success",
      "end": 11.850000000000001,
      "endOffset": 158,
      "phones": [
        {
          "duration": 0.07,
          "phone": "m_B"
        },
        {
          "duration": 0.08,
          "phone": "ah_I"
        },
        {
          "duration": 0.07,
          "phone": "ch_E"
        }
      ],
      "start": 11.63,
      "startOffset": 154,
      "word": "MUCH"
    },
    {
      "alignedWord": "into",
      "case": "success",
      "end": 12.059999000000001,
      "endOffset": 163,
      "phones": [
        {
          "duration": 0.06,
          "phone": "ih_B"
        },
        {
          "duration": 0.05,
          "phone": "n_I"
        },
        {
          "duration": 0.06,
          "phone": "t_I"
        },
        {
          "duration": 0.04,
          "phone": "ah_E"
        }
      ],
      "start": 11.849999,
      "startOffset": 159,
      "word": "INTO"
    },
    {
      "alignedWord": "my",
      "case": "success",
      "end": 12.159999,
      "endOffset": 166,
      "phones": [
        {
          "duration": 0.03,
          "phone": "m_B"
        },
        {
          "duration": 0.07,
          "phone": "ay_E"
        }
      ],
      "start": 12.059999,
      "startOffset": 164,
      "word": "MY"
    },
    {
      "alignedWord": "trunk",
      "case": "success",
      "end": 12.45,
      "endOffset": 172,
      "phones": [
        {
          "duration": 0.08,
          "phone": "t_B"
        },
        {
          "duration": 0.06,
          "phone": "r_I"
        },
        {
          "duration": 0.04,
          "phone": "ah_I"
        },
        {
          "duration": 0.06,
          "phone": "ng_I"
        },
        {
          "duration": 0.05,
          "phone": "k_E"
        }
      ],
      "start": 12.16,
      "startOffset": 167,
      "word": "TRUNK"
    },
    {
      "alignedWord": "as",
      "case": "success",
      "end": 12.549999999999999,
      "endOffset": 175,
      "phones": [
        {
          "duration": 0.05,
          "phone": "eh_B"
        },
        {
          "duration": 0.05,
          "phone": "z_E"
        }
      ],
      "start": 12.45,
      "startOffset": 173,
      "word": "AS"
    },
    {
      "alignedWord": "you",
      "case": "success",
      "end": 12.64,
      "endOffset": 179,
      "phones": [
        {
          "duration": 0.04,
          "phone": "y_B"
        },
        {
          "duration": 0.05,
          "phone": "uw_E"
        }
      ],
      "start": 12.55,
      "startOffset": 176,
      "word": "YOU"
    },
    {
      "alignedWord": "can",
      "case": "success",
      "end": 13.049999,
      "endOffset": 183,
      "phones": [
        {
          "duration": 0.08,
          "phone": "k_B"
        },
        {
          "duration": 0.22,
          "phone": "ae_I"
        },
        {
          "duration": 0.11,
          "phone": "n_E"
        }
      ],
      "start": 12.639999,
      "startOffset": 180,
      "word": "CAN"
    },
    {
      "alignedWord": "my",
      "case": "success",
      "end": 13.209999,
      "endOffset": 186,
      "phones": [
        {
          "duration": 0.09,
          "phone": "m_B"
        },
        {
          "duration": 0.06,
          "phone": "ay_E"
        }
      ],
      "start": 13.059999,
      "startOffset": 184,
      "word": "MY"
    },
    {
      "alignedWord": "traveling",
      "case": "success",
      "end": 13.670000000000002,
      "endOffset": 196,
      "phones": [
        {
          "duration": 0.08,
          "phone": "t_B"
        },
        {
          "duration": 0.08,
          "phone": "r_I"
        },
        {
          "duration": 0.07,
          "phone": "ae_I"
        },
        {
          "duration": 0.06,
          "phone": "v_I"
        },
        {
          "duration": 0.05,
          "phone": "l_I"
        },
        {
          "duration": 0.06,
          "phone": "ih_I"
        },
        {
          "duration": 0.06,
          "phone": "ng_E"
        }
      ],
      "start": 13.21,
      "startOffset": 187,
      "word": "TRAVELING"
    },
    {
      "alignedWord": "kit",
      "case": "success",
      "end": 13.9,
      "endOffset": 200,
      "phones": [
        {
          "duration": 0.08,
          "phone": "k_B"
        },
        {
          "duration": 0.08,
          "phone": "ih_I"
        },
        {
          "duration": 0.07,
          "phone": "t_E"
        }
      ],
      "start": 13.67,
      "startOffset": 197,
      "word": "KIT"
    },
    {
      "alignedWord": "my",
      "case": "success",
      "end": 14.07,
      "endOffset": 203,
      "phones": [
        {
          "duration": 0.06,
          "phone": "m_B"
        },
        {
          "duration": 0.1,
          "phone": "ay_E"
        }
      ],
      "start": 13.91,
      "startOffset": 201,
      "word": "MY"
    },
    {
      "alignedWord": "suits",
      "case": "success",
      "end": 14.5,
      "endOffset": 209,
      "phones": [
        {
          "duration": 0.15,
          "phone": "s_B"
        },
        {
          "duration": 0.1,
          "phone": "uw_I"
        },
        {
          "duration": 0.1,
          "phone": "t_I"
        },
        {
          "duration": 0.08,
          "phone": "s_E"
        }
      ],
      "start": 14.07,
      "startOffset": 204,
      "word": "SUITS"
    },
    {
      "alignedWord": "shirts",
      "case": "success",
      "end": 14.829999,
      "endOffset": 216,
      "phones": [
        {
          "duration": 0.15,
          "phone": "sh_B"
        },
        {
          "duration": 0.08,
          "phone": "er_I"
        },
        {
          "duration": 0.06,
          "phone": "t_I"
        },
        {
          "duration": 0.03,
          "phone": "s_E"
        }
      ],
      "start": 14.509999,
      "startOffset": 210,
      "word": "SHIRTS"
    },
    {
      "alignedWord": "and",
      "case": "success",
      "end": 14.98,
      "endOffset": 220,
      "phones": [
        {
          "duration": 0.05,
          "phone": "ah_B"
        },
        {
          "duration": 0.04,
          "phone": "n_I"
        },
        {
          "duration": 0.06,
          "phone": "d_E"
        }
      ],
      "start": 14.83,
      "startOffset": 217,
      "word": "AND"
    },
    {
      "alignedWord": "socks",
      "case": "success",
      "end": 15.47,
      "endOffset": 226,
      "phones": [
        {
          "duration": 0.11,
          "phone": "s_B"
        },
        {
          "duration": 0.16,
          "phone": "aa_I"
        },
        {
          "duration": 0.11,
          "phone": "k_I"
        },
        {
          "duration": 0.11,
          "phone": "s_E"
        }
      ],
      "start": 14.98,
      "startOffset": 221,
      "word": "SOCKS"
    }
  ]
}