{
  "transcript": "IT DOES NOT FUNCTION AS A PHYSICAL QUALITY BUT THE CARRION TURNS OUR STOMACH BY WHAT SEEMS A DIRECT OPERATION IT DOES FUNCTION PHYSICALLY THEREFORE IN THAT LIMITED PART OF PHYSICS",
  "words": [
    {
      "alignedWord": "it",
      "case": "success",
      "end": 0.48,
      "endOffset": 2,
      "phones": [
        {
          "duration": 0.1,
          "phone": "ih_B"
        },
        {
          "duration": 0.03,
          "phone": "t_E"
        }
      ],
      "start": 0.35,
      "startOffset": 0,
      "word": "IT"
    },
    {
      "alignedWord": "does",
      "case": "success",
      "end": 0.67,
      "endOffset": 7,
      "phones": [
        {
          "duration": 0.05,
          "phone": "d_B"
        },
        {
          "duration": 0.05,
          "phone": "ih_I"
        },
        {
          "duration": 0.07,
          "phone": "z_E"
        }
      ],
      "start": 0.5,
      "startOffset": 3,
      "word": "DOES"
    },
    {
      "alignedWord": "not",
      "case": "success",
      "end": 0.88,
      "endOffset": 11,
      "phones": [
        {
          "duration": 0.04,
          "phone": "n_B"
        },
        {
          "duration": 0.09,
          "phone": "aa_I"
        },
        {
          "duration": 0.08,
          "phone": "t_E"
        }
      ],
      "start": 0.67,
      "startOffset": 8,
      "word": "NOT"
    },
    {
      "alignedWord": "function",
      "case": "success",
      "end": 1.31,
      "endOffset": 20,
      "phones": [
        {
          "duration": 0.09,
          "phone": "f_B"
        },
        {
          "duration": 0.05,
          "phone": "ah_I"
        },
        {
          "duration": 0.06,
          "phone": "ng_I"
        },
        {
          "duration": 0.04,
          "phone": "k_I"
        },
        {
          "duration": 0.06,
          "phone": "sh_I"
        },
        {
          "duration": 0.06,
          "phone": "ah_I"
        },
        {
          "duration": 0.07,
          "phone": "n_E"
        }
      ],
      "start": 0.88,
      "startOffset": 12,
      "word": "FUNCTION"
    },
    {
      "alignedWord": "as",
      "case": "success",
      "end": 1.47,
      "endOffset": 23,
      "phones": [
        {
          "duration": 0.08,
          "phone": "ae_B"
        },
        {
          "duration": 0.08,
          "phone": "z_E"
        }
      ],
      "start": 1.31,
      "startOffset": 21,
      "word": "AS"
    },
    {
      "alignedWord": "a",
      "case": "success",
      "end": 1.57,
      "endOffset": 25,
      "phones": [
        {
          "duration": 0.1,
          "phone": "ey_S"
        }
      ],
      "start": 1.47,
      "startOffset": 24,
      "word": "A"
    },
    {
      "alignedWord": "physical",
      "case": "success",
      "end": 1.98,
      "endOffset": 34,
      "phones": [
        {
          "duration": 0.08,
          "phone": "f_B"
        },
        {
          "duration": 0.04,
          "phone": "ih_I"
        },
        {
          "duration": 0.05,
          "phone": "z_I"
        },
        {
          "duration": 0.09,
          "phone": "ih_I"
        },
        {
          "duration": 0.02,
          "phone": "k_I"
        },
        {
          "duration": 0.08,
          "phone": "ah_I"
        },
        {
          "duration": 0.04,
          "phone": "l_E"
        }
      ],
      "start": 1.58,
      "startOffset": 26,
      "word": "PHYSICAL"
    },
    {
      "alignedWord": "quality",
      "case": "success",
      "end": 2.4699999999999998,
      "endOffset": 42,
      "phones": [
        {
          "duration": 0.09,
          "phone": "k_B"
        },
        {
          "duration": 0.05,
          "phone": "w_I"
        },
        {
          "duration": 0.07,
          "phone": "aa_I"
        },
        {
          "duration": 0.04,
          "phone": "l_I"
        },
        {
          "duration": 0.06,
          "phone": "ah_I"
        },
        {
          "duration": 0.05,
          "phone": "t_I"
        },
        {
          "duration": 0.13,
          "phone": "iy_E"
        }
      ],
      "start": 1.98,
      "startOffset": 35,
      "word": "QUALITY"
    },
    {
      "alignedWord": "but",
      "case": "success",
      "end": 4.04,
      "endOffset": 46,
      "phones": [
        {
          "duration": 0.08,
          "phone": "b_B"
        },
        {
          "duration": 0.06,
          "phone": "ah_I"
        },
        {
          "duration": 0.06,
          "phone": "t_E"
        }
      ],
      "start": 3.84,
      "startOffset": 43,
      "word": "BUT"
    },
    {
      "alignedWord": "the",
      "case": "success",
      "end": 4.19,
      "endOffset": 50,
      "phones": [
        {
          "duration": 0.05,
          "phone": "dh_B"
        },
        {
          "duration": 0.1,
          "phone": "ah_E"
        }
      ],
      "start": 4.04,
      "startOffset": 47,
      "word": "THE"
    },
    {
      "alignedWord": "<unk>",
      "case": "success",
      "end": 4.800000000000001,
      "endOffset": 58,
      "phones": [
        {
          "duration": 0.61,
          "phone": "oov_S"
        }
      ],
      "start": 4.19,
      "startOffset": 51,
      "word": "CARRION"
    },
    {
      "alignedWord": "turns",
      "case": "success",
      "end": 5.4,
      "endOffset": 64,
      "phones": [
        {
          "duration": 0.17,
          "phone": "t_B"
        },
        {
          "duration": 0.12,
          "phone": "er_I"
        },
        {
          "duration": 0.09,
          "phone": "n_I"
        },
        {
          "duration": 0.07,
          "phone": "z_E"
        }
      ],
      "start": 4.95,
      "startOffset": 59,
      "word": "TURNS"
    },
    {
      "alignedWord": "our",
      "case": "success",
      "end": 5.57,
      "endOffset": 68,
      "phones": [
        {
          "duration": 0.08,
          "phone": "aa_B"
        },
        {
          "duration": 0.09,
          "phone": "r_E"
        }
      ],
      "start": 5.4,
      "startOffset": 65,
      "word": "OUR"
    },
    {
      "alignedWord": "stomach",
      "case": "success",
      "end": 6.04,
      "endOffset": 76,
      "phones": [
        {
          "duration": 0.08,
          "phone": "s_B"
        },
        {
          "duration": 0.09,
          "phone": "t_I"
        },
        {
          "duration": 0.04,
          "phone": "ah_I"
        },
        {
          "duration": 0.08,
          "phone": "m_I"
        },
        {
          "duration": 0.08,
          "phone": "ah_I"
        },
        {
          "duration": 0.1,
          "phone": "k_E"
        }
      ],
      "start": 5.57,
      "startOffset": 69,
      "word": "STOMACH"
    },
    {
      "alignedWord": "by",
      "case": "success",
      "end": 6.25,
      "endOffset": 79,
      "phones": [
        {
          "duration": 0.11,
          "phone": "b_B"
        },
        {
          "duration": 0.06,
          "phone": "ay_E"
        }
      ],
      "start": 6.08,
      "startOffset": 77,
      "word": "BY"
    },
    {
      "alignedWord": "what",
      "case": "success",
      "end": 6.53,
      "endOffset": 84,
      "phones": [
        {
          "duration": 0.07,
          "phone": "hh_B"
        },
        {
          "duration": 0.07,
          "phone": "w_I"
        },
        {
          "duration": 0.06,
          "phone": "ah_I"
        },
        {
          "duration": 0.08,
          "phone": "t_E"
        }
      ],
      "start": 6.25,
      "startOffset": 80,
      "word": "WHAT"
    },
    {
      "alignedWord": "seems",
      "case": "success",
      "end": 6.930000000000001,
      "endOffset": 90,
      "phones": [
        {
          "duration": 0.14,
          "phone": "s_B"
        },
        {
          "duration": 0.12,
          "phone": "iy_I"
        },
        {
          "duration": 0.08,
          "phone": "m_I"
        },
        {
          "duration": 0.06,
          "phone": "z_E"
        }
      ],
      "start": 6.53,
      "startOffset": 85,
      "word": "SEEMS"
    },
    {
      "alignedWord": "a",
      "case": "success",
      "end": 7.1000000000000005,
      "endOffset": 92,
      "phones": [
        {
          "duration": 0.15,
          "phone": "ey_S"
        }
      ],
      "start": 6.95,
      "startOffset": 91,
      "word": "A"
    },
    {
      "alignedWord": "direct",
      "case": "success",
      "end": 7.4799999999999995,
      "endOffset": 99,
      "phones": [
        {
          "duration": 0.08,
          "phone": "d_B"
        },
        {
          "duration": 0.1,
          "phone": "er_I"
        },
        {
          "duration": 0.06,
          "phone": "eh_I"
        },
        {
          "duration": 0.06,
          "phone": "k_I"
        },
        {
          "duration": 0.08,
          "phone": "t_E"
        }
      ],
      "start": 7.1,
      "startOffset": 93,
      "word": "DIRECT"
    },
    {
      "alignedWord": "operation",
      "case": "success",
      "end": 8.25,
      "endOffset": 109,
      "phones": [
        {
          "duration": 0.12,
          "phone": "aa_B"
        },
        {
          "duration": 0.11,
          "phone": "p_I"
        },
        {
          "duration": 0.1,
          "phone": "er_I"
        },
        {
          "duration": 0.1,
          "phone": "ey_I"
        },
        {
          "duration": 0.11,
          "phone": "sh_I"
        },
        {
          "duration": 0.06,
          "phone": "ah_I"
        },
        {
          "duration": 0.14,
          "phone": "n_E"
        }
      ],
      "start": 7.51,
      "startOffset": 100,
      "word": "OPERATION"
    },
    {
      "alignedWord": "it",
      "case": "success",
      "end": 9.3,
      "endOffset": 112,
      "phones": [
        {
          "duration": 0.14,
          "phone": "ih_B"
        },
        {
          "duration": 0.11,
          "phone": "t_E"
        }
      ],
      "start": 9.05,
      "startOffset": 110,
      "word": "IT"
    },
    {
      "alignedWord": "does",
      "case": "success",
      "end": 9.74,
      "endOffset": 117,
      "phones": [
        {
          "duration": 0.1,
          "phone": "d_B"
        },
        {
          "duration": 0.13,
          "phone": "ah_I"
        },
        {
          "duration": 0.1,
          "phone": "z_E"
        }
      ],
      "start": 9.41,
      "startOffset": 113,
      "word": "DOES"
    },
    {
      "alignedWord": "function",
      "case": "success",
      "end": 10.19,
      "endOffset": 126,
      "phones": [
        {
          "duration": 0.09,
          "phone": "f_B"
        },
        {
          "duration": 0.06,
          "phone": "ah_I"
        },
        {
          "duration": 0.06,
          "phone": "ng_I"
        },
        {
          "duration": 0.03,
          "phone": "k_I"
        },
        {
          "duration": 0.07,
          "phone": "sh_I"
        },
        {
          "duration": 0.06,
          "phone": "ah_I"
        },
        {
          "duration": 0.08,
          "phone": "n_E"
        }
      ],
      "start": 9.74,
      "startOffset": 118,
      "word": "FUNCTION"
    },
    {
      "alignedWord": "physically",
      "case": "success",
      "end": 10.68,
      "endOffset": 137,
      "phones": [
        {
          "duration": 0.09,
          "phone": "f_B"
        },
        {
          "duration": 0.05,
          "phone": "ih_I"
        },
        {
          "duration": 0.05,
          "phone": "z_I"
        },
        {
          "duration": 0.09,
          "phone": "ih_I"
        },
        {
          "duration": 0.07,
          "phone": "k_I"
        },
        {
          "duration": 0.06,
          "phone": "l_I"
        },
        {
          "duration": 0.07,
          "phone": "iy_E"
        }
      ],
      "start": 10.2,
      "startOffset": 127,
      "word": "PHYSICALLY"
    },
    {
      "alignedWord": "therefore",
      "case": "success",
      "end": 11.219999000000001,
      "endOffset": 147,
      "phones": [
        {
          "duration": 0.06,
          "phone": "dh_B"
        },
        {
          "duration": 0.05,
          "phone": "eh_I"
        },
        {
          "duration": 0.09,
          "phone": "r_I"
        },
        {
          "duration": 0.12,
          "phone": "f_I"
        },
        {
          "duration": 0.08,
          "phone": "ao_I"
        },
        {
          "duration": 0.14,
          "phone": "r_E"
        }
      ],
      "start": 10.679999,
      "startOffset": 138,
      "word": "THEREFORE"
    },
    {
      "alignedWord": "in",
      "case": "success",
      "end": 11.790000000000001,
      "endOffset": 150,
      "phones": [
        {
          "duration": 0.13,
          "phone": "ih_B"
        },
        {
          "duration": 0.09,
          "phone": "n_E"
        }
      ],
      "start": 11.57,
      "startOffset": 148,
      "word": "IN"
    },
    {
      "alignedWord": "that",
      "case": "success",
      "end": 12.08,
      "endOffset": 155,
      "phones": [
        {
          "duration": 0.08,
          "phone": "dh_B"
        },
        {
          "duration": 0.1,
          "phone": "ae_I"
        },
        {
          "duration": 0.1,
          "phone": "t_E"
        }
      ],
      "start": 11.8,
      "startOffset": 151,
      "word": "THAT"
    },
    {
      "alignedWord": "limited",
      "case": "success",
      "end": 12.5,
      "endOffset": 163,
      "phones": [
        {
          "duration": 0.07,
          "phone": "l_B"
        },
        {
          "duration": 0.05,
          "phone": "ih_I"
        },
        {
          "duration": 0.04,
          "phone": "m_I"
        },
        {
          "duration": 0.06,
          "phone": "ih_I"
        },
        {
          "duration": 0.04,
          "phone": "t_I"
        },
        {
          "duration": 0.06,
          "phone": "ih_I"
        },
        {
          "duration": 0.09,
          "phone": "d_E"
        }
      ],
      "start": 12.09,
      "startOffset": 156,
      "word": "LIMITED"
    },
    {
      "alignedWord": "part",
      "case": "success",
      "end": 12.78,
      "endOffset": 168,
      "phones": [
        {
          "duration": 0.08,
          "phone": "p_B"
        },
        {
          "duration": 0.07,
          "phone": "aa_I"
        },
        {
          "duration": 0.06,
          "phone": "r_I"
        },
        {
          "duration": 0.07,
          "phone": "t_E"
        }
      ],
      "start": 12.5,
      "startOffset": 164,
      "word": "PART"
    },
    {
      "alignedWord": "of",
      "case": "success",
      "end": 12.95,
      "endOffset": 171,
      "phones": [
        {
          "duration": 0.09,
          "phone": "ah_B"
        },
        {
          "duration": 0.07,
          "phone": "v_E"
        }
      ],
      "start": 12.79,
      "startOffset": 169,
      "word": "OF"
    },
    {
      "alignedWord": "physics",
      "case": "success",
      "end": 13.510000000000002,
      "endOffset": 179,
      "phones": [
        {
          "duration": 0.09,
          "phone": "f_B"
        },
        {
          "duration": 0.08,
          "phone": "ih_I"
        },
        {
          "duration": 0.06,
          "phone": "z_I"
        },
        {
          "duration": 0.06,
          "phone": "ih_I"
        },
        {
          "duration": 0.1,
          "phone": "k_I"
        },
        {
          "duration": 0.16,
          "phone": "s_E"
        }
      ],
      "start": 12.96,
      "startOffset": 172,
      "word": "PHYSICS"
    }
  ]
}